git_smudge/__init__.py
git_smudge/__main__.py
git_smudge/config.py
git_smudge/filters.py
git_smudge/runfilter.py
git_smudge/tests.py
git_smudge-0.0.21.dist-info/LICENSE
git_smudge-0.0.21.dist-info/METADATA
git_smudge-0.0.21.dist-info/WHEEL
git_smudge-0.0.21.dist-info/entry_points.txt
git_smudge-0.0.21.dist-info/top_level.txt
git_smudge-0.0.21.dist-info/RECORD
