Metadata-Version: 2.1
Name: git_smudge
Version: 0.0.21
Summary: A powerful filter driver for Git which can automatically apply local changes to the working tree of a repository
Home-page: https://ktpanda.org/software/git_smudge
Author: Katie Rust
Author-email: katie@ktpanda.org
License: MIT License
Classifier: Programming Language :: Python :: 3
Classifier: License :: OSI Approved :: MIT License
Classifier: Operating System :: OS Independent
Requires-Python: >=3.8
License-File: LICENSE
Requires-Dist: argcomplete >=2.0.0
Requires-Dist: ktpanda-modules >=1.0.33
Requires-Dist: tomli >=2.0.0 ; python_version < "3.11"
